LICENSE
MANIFEST.in
README.rst
setup.cfg
setup.py
tests/__init__.py
tests/conftest.py
tests/api/__init__.py
tests/api/test_bot.py
tests/api/chats/__init__.py
tests/api/messages/__init__.py
tests/ext/__init__.py
tests/utils/__init__.py
wxpy/__init__.py
wxpy/__main__.py
wxpy/exceptions.py
wxpy.egg-info/PKG-INFO
wxpy.egg-info/SOURCES.txt
wxpy.egg-info/dependency_links.txt
wxpy.egg-info/entry_points.txt
wxpy.egg-info/requires.txt
wxpy.egg-info/top_level.txt
wxpy/api/__init__.py
wxpy/api/bot.py
wxpy/api/consts.py
wxpy/api/chats/__init__.py
wxpy/api/chats/chat.py
wxpy/api/chats/chats.py
wxpy/api/chats/friend.py
wxpy/api/chats/group.py
wxpy/api/chats/groups.py
wxpy/api/chats/member.py
wxpy/api/chats/mp.py
wxpy/api/chats/user.py
wxpy/api/messages/__init__.py
wxpy/api/messages/message.py
wxpy/api/messages/message_config.py
wxpy/api/messages/messages.py
wxpy/api/messages/registered.py
wxpy/api/messages/sent_message.py
wxpy/ext/__init__.py
wxpy/ext/logging_with_wechat.py
wxpy/ext/sync_message_in_groups.py
wxpy/ext/talk_bot_utils.py
wxpy/ext/tuling.py
wxpy/ext/xiaoi.py
wxpy/utils/__init__.py
wxpy/utils/base_request.py
wxpy/utils/console.py
wxpy/utils/misc.py
wxpy/utils/puid_map.py
wxpy/utils/tools.py