Metadata-Version: 1.1
Name: wxpy
Version: 0.3.9.6
Summary: 微信机器人 / 优雅而强大的微信个人号 API
Home-page: https://github.com/youfou/wxpy
Author: Youfou
Author-email: youfou@qq.com
License: MIT
Keywords: 微信,WeChat,API
Platform: UNKNOWN
Classifier: Development Status :: 4 - Beta
Classifier: License :: OSI Approved :: MIT License
Classifier: Programming Language :: Python :: 3
Classifier: Operating System :: OS Independent
Classifier: Topic :: Communications :: Chat
Classifier: Topic :: Utilities
